deltaprocessor/__init__.py
deltaprocessor/block.py
deltaprocessor/delta_process.py
deltaprocessor/document.py
deltaprocessor/node.py
deltaprocessor/render.py
deltaprocessor-0.1.0.dist-info/METADATA
deltaprocessor-0.1.0.dist-info/WHEEL
deltaprocessor-0.1.0.dist-info/top_level.txt
deltaprocessor-0.1.0.dist-info/RECORD
